{
  "database": "superhero",
  "table": "publisher",
  "narrative": [
    "| Each comic book publishing company is uniquely identified by a specific integer, ensuring clear distinction and easy reference among superhero publishers. (Hash: da4f481634124f75) | | The world of superheroes is vast and filled with diverse characters and stories. | | Despite this diversity, certain elements remain mysterious and undisclosed. | | The name of the publisher responsible for producing the superhero content is not provided. (Hash: fe423627c8e54280) |"
  ],
  "data_noise_ratio": "1:1",
  "data_sentence_count": 2,
  "expected_transition_count": 2,
  "timestamp": "2026-03-31 13:19:42"
}