{
  "database": "formula_1",
  "table": "seasons",
  "narrative": [
    "| The inaugural Formula 1 championship season took place in 1950, marking the beginning of a prestigious motor racing era. (Hash: 1e5a128fcd824809) | | For more details about the inaugural season of Formula 1 racing in 1950, visit http://en.wikipedia.org/wiki/1950_Formula_One_season. (Hash: eba3b9b8a40f4a92) |"
  ],
  "data_noise_ratio": "1:0",
  "data_sentence_count": 2,
  "expected_transition_count": 0,
  "timestamp": "2026-04-13 02:07:56"
}